{
  "version": 0.6,
  "generator": "Overpass API 0.7.62.5 1bd436f1",
  "osm3s": {
    "timestamp_osm_base": "2025-02-15T00:13:36Z",
    "copyright": "The data included in this document is from www.openstreetmap.org. The data is made available under ODbL."
  },
  "elements": [
    {
      "type": "node",
      "id": 369025901,
      "lat": 41.0960209,
      "lon": 0.9713535
    },
    {
      "type": "node",
      "id": 369025902,
      "lat": 41.0959821,
      "lon": 0.97126
    },
    {
      "type": "node",
      "id": 369025904,
      "lat": 41.098056,
      "lon": 0.9687164
    },
    {
      "type": "node",
      "id": 369025905,
      "lat": 41.100118,
      "lon": 0.966006
    },
    {
      "type": "node",
      "id": 369025906,
      "lat": 41.1029482,
      "lon": 0.9623043
    },
    {
      "type": "node",
      "id": 369025907,
      "lat": 41.1034001,
      "lon": 0.9615936
    },
    {
      "type": "node",
      "id": 369025909,
      "lat": 41.1069055,
      "lon": 0.9560298
    },
    {
      "type": "node",
      "id": 369025910,
      "lat": 41.1087916,
      "lon": 0.9530305
    },
    {
      "type": "node",
      "id": 369025911,
      "lat": 41.1089083,
      "lon": 0.9527534
    },
    {
      "type": "node",
      "id": 369025912,
      "lat": 41.1093259,
      "lon": 0.9508708
    },
    {
      "type": "node",
      "id": 369025913,
      "lat": 41.109536,
      "lon": 0.950071
    },
    {
      "type": "node",
      "id": 369025914,
      "lat": 41.1107853,
      "lon": 0.9472497
    },
    {
      "type": "node",
      "id": 369025915,
      "lat": 41.110985,
      "lon": 0.9461008
    },
    {
      "type": "node",
      "id": 369025916,
      "lat": 41.111613,
      "lon": 0.9435111
    },
    {
      "type": "node",
      "id": 369027376,
      "lat": 41.1120703,
      "lon": 0.9419047
    },
    {
      "type": "node",
      "id": 369047824,
      "lat": 41.1118351,
      "lon": 0.9427409
    },
    {
      "type": "node",
      "id": 533763874,
      "lat": 41.0961877,
      "lon": 0.9710504
    },
    {
      "type": "node",
      "id": 533763880,
      "lat": 41.0960666,
      "lon": 0.9711326
    },
    {
      "type": "node",
      "id": 533763882,
      "lat": 41.0960812,
      "lon": 0.9712415
    },
    {
      "type": "node",
      "id": 533973551,
      "lat": 41.1090696,
      "lon": 0.9522124
    },
    {
      "type": "node",
      "id": 533973552,
      "lat": 41.109165,
      "lon": 0.9518342
    },
    {
      "type": "node",
      "id": 533973553,
      "lat": 41.1092014,
      "lon": 0.9515891
    },
    {
      "type": "node",
      "id": 533973554,
      "lat": 41.1092422,
      "lon": 0.9513482
    },
    {
      "type": "node",
      "id": 533973555,
      "lat": 41.1092862,
      "lon": 0.9511229
    },
    {
      "type": "node",
      "id": 533973556,
      "lat": 41.1093675,
      "lon": 0.9505527
    },
    {
      "type": "node",
      "id": 533973557,
      "lat": 41.1110713,
      "lon": 0.9454138
    },
    {
      "type": "node",
      "id": 533973558,
      "lat": 41.111025,
      "lon": 0.9465202
    },
    {
      "type": "node",
      "id": 533973559,
      "lat": 41.1109321,
      "lon": 0.9458787
    },
    {
      "type": "node",
      "id": 533973560,
      "lat": 41.1110321,
      "lon": 0.9456424
    },
    {
      "type": "node",
      "id": 1799147213,
      "lat": 41.1111111,
      "lon": 0.9457789
    },
    {
      "type": "node",
      "id": 1799147216,
      "lat": 41.1109884,
      "lon": 0.9457455
    },
    {
      "type": "node",
      "id": 1799147218,
      "lat": 41.1111273,
      "lon": 0.9459827
    },
    {
      "type": "node",
      "id": 2687517010,
      "lat": 41.1044945,
      "lon": 0.9598566
    },
    {
      "type": "node",
      "id": 2721237366,
      "lat": 41.0995534,
      "lon": 0.9667481
    },
    {
      "type": "node",
      "id": 2721237385,
      "lat": 41.1011942,
      "lon": 0.9645985
    },
    {
      "type": "node",
      "id": 7890406205,
      "lat": 41.106684,
      "lon": 0.9563814
    },
    {
      "type": "node",
      "id": 12536257089,
      "lat": 41.100845,
      "lon": 0.9650534
    },
    {
      "type": "node",
      "id": 12536257090,
      "lat": 41.1006307,
      "lon": 0.965327
    },
    {
      "type": "way",
      "id": 42683735,
      "nodes": [
        369025901,
        533763882,
        533763874
      ],
      "tags": {
        "highway": "tertiary",
        "oneway": "yes",
        "ref": "T-321"
      }
    },
    {
      "type": "way",
      "id": 42683736,
      "nodes": [
        12536257089,
        2721237385,
        369025906,
        369025907,
        2687517010,
        7890406205,
        369025909,
        369025910,
        369025911,
        533973551,
        533973552,
        533973553,
        533973554,
        533973555,
        369025912,
        533973556,
        369025913,
        369025914,
        533973558,
        369025915,
        533973559,
        1799147216,
        533973560,
        533973557,
        369025916,
        369047824,
        369027376
      ],
      "tags": {
        "highway": "tertiary",
        "oneway": "no",
        "ref": "T-321"
      }
    },
    {
      "type": "way",
      "id": 168687035,
      "nodes": [
        1799147216,
        1799147213,
        1799147218,
        369025915
      ],
      "tags": {
        "highway": "tertiary",
        "oneway": "no",
        "ref": "T-321"
      }
    },
    {
      "type": "way",
      "id": 1085862367,
      "nodes": [
        533763880,
        369025902
      ],
      "tags": {
        "highway": "tertiary",
        "oneway": "yes",
        "ref": "T-321"
      }
    },
    {
      "type": "way",
      "id": 1085862369,
      "nodes": [
        533763874,
        533763880
      ],
      "tags": {
        "highway": "tertiary",
        "oneway": "yes",
        "ref": "T-321"
      }
    },
    {
      "type": "way",
      "id": 1354640339,
      "nodes": [
        12536257090,
        12536257089
      ],
      "tags": {
        "bridge": "yes",
        "highway": "tertiary",
        "layer": "1",
        "oneway": "no",
        "ref": "T-321"
      }
    },
    {
      "type": "way",
      "id": 1354640340,
      "nodes": [
        533763874,
        369025904,
        2721237366,
        369025905,
        12536257090
      ],
      "tags": {
        "highway": "tertiary",
        "oneway": "no",
        "ref": "T-321"
      }
    }
  ]
}